tokengrams-0.3.3.dist-info/METADATA
tokengrams-0.3.3.dist-info/WHEEL
tokengrams-0.3.3.dist-info/licenses/LICENSE.md
tokengrams/benchmark/benchmark.py
tokengrams/benchmark/InMemoryIndex_build_times.png
tokengrams/benchmark/InMemoryIndex_count_next_times.png
tokengrams/benchmark/MemmapIndex_build_times.png
tokengrams/benchmark/MemmapIndex_count_next_times.png
tokengrams/tests/test_gram_index.py
tokengrams/tests/test_sharded_index.py
tokengrams/tests/__init__.py
tokengrams/tokengrams.pyi
tokengrams/utils/tokenize_hf_dataset.py
tokengrams/utils/__init__.py
tokengrams/__init__.py
tokengrams/tokengrams.cp310-win_amd64.pyd
tokengrams-0.3.3.dist-info/RECORD
