Metadata-Version: 2.3
Name: tokengrams
Version: 0.3.3
Requires-Dist: numpy >=1.24.4
Requires-Dist: datasets >=1.14.0
Requires-Dist: transformers >=4.11.3
Requires-Dist: tqdm >=4.0.0
License-File: LICENSE.md
Summary: Efficiently computing & storing token n-grams from large corpora 
Author-email: Nora Belrose <nora@eleuther.ai>, Lucia Quirke <lucia@eleuther.ai>
License: MIT
Requires-Python: >=3.10
